metals_api_zylalabs/__init__.py
metals_api_zylalabs/client.py
metals_api_zylalabs-0.5.dist-info/METADATA
metals_api_zylalabs-0.5.dist-info/WHEEL
metals_api_zylalabs-0.5.dist-info/top_level.txt
metals_api_zylalabs-0.5.dist-info/RECORD
